LICENSE
README.md
setup.py
bdbt/__init__.py
bdbt/exporter.py
bdbt/global_type.py
bdbt/logging_utils.py
bdbt/utils.py
bdbt/cli/__init__.py
bdbt/cli/ethereum_codegen.py
bdbt/cli/export_added_nft_metadata.py
bdbt/cli/export_all_nft_metadata.py
bdbt/ethereum/__init__.py
bdbt/ethereum/exceptions.py
bdbt/ethereum/abi/__init__.py
bdbt/ethereum/abi/abi_data_type.py
bdbt/ethereum/abi/abi_transformer.py
bdbt/ethereum/abi/abi_type.py
bdbt/ethereum/abi/utils.py
bdbt/ethereum/abi/provider/__init__.py
bdbt/ethereum/abi/provider/data_type_provider.py
bdbt/ethereum/abi/provider/hive_object_inspector_type_provider.py
bdbt/ethereum/abi/provider/spark_type_provider.py
bdbt/ethereum/dbt/__init__.py
bdbt/ethereum/dbt/dbt_code_generator.py
bdbt/ethereum/dbt/dbt_factory.py
bdbt/ethereum/dbt/dbt_generator.py
bdbt/ethereum/dbt/dbt_schema_generator.py
bdbt/ethereum/dbt/spark/__init__.py
bdbt/ethereum/dbt/spark/spark_dbt_code_generator.py
bdbt/external/__init__.py
bdbt/external/export_nft_metadata_job.py
bdbt/external/clients/__init__.py
bdbt/external/clients/moralis.py
bdbt/external/executors/__init__.py
bdbt/external/executors/batch_work_executor.py
bdbt/external/executors/bounded_executor.py
bdbt/external/executors/fail_safe_executor.py
bdbt/external/executors/progress_logger.py
blockchain_dbt.egg-info/PKG-INFO
blockchain_dbt.egg-info/SOURCES.txt
blockchain_dbt.egg-info/dependency_links.txt
blockchain_dbt.egg-info/entry_points.txt
blockchain_dbt.egg-info/requires.txt
blockchain_dbt.egg-info/top_level.txt