Metadata-Version: 2.1
Name: blockchain-dbt
Version: 0.4.0
Summary: The schema transformer and dbt utils for blockchain data.
Home-page: https://github.com/datawaves/blockchain-dbt
Author: Datawaves
Author-email: team@datawaves.xyz
License: UNKNOWN
Project-URL: Bug Reports, https://github.com/datawaves/blockchain-dbt/issues
Project-URL: Source, https://github.com/datawaves/blockchain-dbt
Keywords: blockchain,dbt
Platform: UNKNOWN
Classifier: Development Status :: 5 - Production/Stable
Classifier: Intended Audience :: Developers
Classifier: License :: OSI Approved :: MIT License
Classifier: Programming Language :: Python :: 3.8
Classifier: Programming Language :: Python :: 3.9
Requires-Python: >=3.8,<4
Provides-Extra: dev
